{
  "category": "xa-hoi",
  "url": "https://vtv.vn/xa-hoi/san-bay-tan-son-nhat-co-xe-bus-mien-phi-tu-ga-t3-sang-t1-20250501094646022.htm",
  "source": "vtv",
  "scraped_at": "2025-05-07 20:20:23",
  "summary": "VTV.vn - Từ 1/5, hành khách transit tại sân bay Tân Sơn Nhất sẽ được đưa đón miễn phí bằng xe buýt bên trong sân đậu, kết nối nhà ga T3 với T1.",
  "content": "Nhằm phục vụ hành khách transit thuận tiện hơn khi nối chuyến từ nhà ga T3 sang T1, từ ngày 1/5/2025, Cảng Hàng không quốc tế Tân Sơn Nhất đã triển khai tuyến xe shuttle bus (miễn phí) hoạt động bên trong sân đậu tàu bay.Lộ trình:Tuyến xe di chuyển từ sảnh Transit nhà ga T3, đi qua sân đậu tàu bay, kết thúc tại cửa A2 nhà ga T1.Thời gian hoạt động: từ 7h00 đến 3h00 sáng hôm sau.Tần suất: mỗi 20 phút/chuyến.Hành khách di chuyển bằng shuttle bus qua nhà ga T1, T2 qua cửa nhập A2 để nối chuyến, sáng 1/5.Tuyến xe này chỉ áp dụng một chiều từ T3 sang T1, dành riêng cho hành khách nối chuyến (transit) đã hoàn tất thủ tục và có thẻ lên tàu bay chặng tiếp theo. Hành lý ký gửi cũng đã được các hãng hàng không chuyển tiếp trước đó.Theo ghi nhận tại hiện trường, nhiều hành khách đã bắt đầu sử dụng tuyến shuttle bus này để di chuyển từ T3 đến cửa nhập A2, sau đó tiếp tục các chuyến bay quốc nội tại ga T1 hoặc quốc tế tại ga T2 theo đúng lộ trình.* Mời quý độc giả theo dõi các chương trình đã phát sóng của Đài Truyền hình Việt Nam trên TV Online và VTVGo!"
}