{
  "category": "giao-duc",
  "url": "https://vtv.vn/giao-duc/ha-noi-co-them-412-truong-hoc-dat-chuan-quoc-gia-20250404211705121.htm",
  "source": "vtv",
  "scraped_at": "2025-05-07 22:07:34",
  "summary": "VTV.vn - Ngày 4/4, Sở Giáo dục và Đào tạo Hà Nội tổ chức trao bằng công nhận cho 412 trường học đạt chuẩn quốc gia năm 2024.",
  "content": "Theo đánh giá của Sở GD&ĐT Hà Nội, trong xu thế đổi mới giáo dục, việc xây dựng và duy trì hệ thống trường chuẩn quốc gia không chỉ khẳng định chất lượng dạy và học mà còn thể hiện cam kết mạnh mẽ của ngành giáo dục trong việc kiến tạo môi trường học tập hiện đại, an toàn, thân thiện và hiệu quả.Năm 2024, thành phố Hà Nội ghi nhận 412 trường đạt chuẩn quốc gia, trong đó có 128 trường được công nhận mới và 284 trường được công nhận lại, nâng tỷ lệ trường chuẩn toàn thành phố lên 61,4%, riêng khối công lập đạt 75,8%.Đáng chú ý, trong số 128 trường học được công nhận mới năm 2024, có 64 trường được công nhận đạt chuẩn quốc gia mức độ 1; 64 trường được công nhận đạt chuẩn quốc gia mức độ 2.Tính theo cấp học, năm 2024, cấp mầm non có thêm số trường được công nhận đạt chuẩn quốc gia nhiều nhất với 53 trường; cấp tiểu học có thêm 44 trường, cấp trung học cơ sở có thêm 28 trường, cấp trung học phổ thông có thêm 3 trường.Để đạt chuẩn quốc gia, mỗi nhà trường phải đáp ứng 5 tiêu chí quan trọng: Công tác quản lý; cơ sở vật chất; đội ngũ giáo viên; chất lượng giảng dạy; sự phối hợp giữa gia đình - nhà trường - xã hội. Đặc biệt, các nhà trường ngày càng đẩy mạnh ứng dụng công nghệ thông tin, đổi mới phương pháp giảng dạy, tạo nên môi trường học tập tiên tiến, bắt kịp xu hướng giáo dục hiện đại.Theo Giám đốc Sở GD&ĐT Hà Nội Trần Thế Cương, những năm gần đây, chính quyền các quận, huyện, thị xã đã chú trọng quy hoạch và mở rộng diện tích trường học, nhiều trường được xây dựng trên khuôn viên rộng hơn 1 héc ta với thiết kế hiện đại, đồng bộ, tích hợp đầy đủ các khu chức năng như phòng học thông minh, khu thực hành, thư viện mở và sân thể thao đạt chuẩn.Kết quả xây dựng trường chuẩn quốc gia năm 2024 là minh chứng cho sự chuyển mình mạnh mẽ của giáo dục Thủ đô, hướng tới xây dựng một hệ thống giáo dục tiên tiến, đáp ứng yêu cầu hội nhập quốc tế.Hà Nội đặt mục tiêu đến hết năm 2025, tỷ lệ trường học đạt chuẩn quốc gia đạt từ 80% đến 85%. Hiện tại, HĐND thành phố Hà Nội đã phê duyệt chủ trương đầu tư 4 dự án là các trường phổ thông có nhiều cấp học tiên tiến, hiện đại tại huyện Thạch Thất, Gia Lâm, Đông Anh và Thanh Trì.* Mời quý độc giả theo dõi các chương trình đã phát sóng của Đài Truyền hình Việt Nam trên TV Online và VTVGo!"
}