{
  "category": "xa-hoi",
  "url": "https://vtv.vn/xa-hoi/dau-loang-lan-rong-gan-30ha-rung-can-gio-thiet-hai-thuy-san-hon-33-tan-20250505183414101.htm",
  "source": "vtv",
  "scraped_at": "2025-05-07 20:21:34",
  "summary": "VTV.vn - Suốt 10 ngày qua, các cơ quan chức năng vẫn đang khẩn trương khắc phục sự cố va chạm giữa 2 tàu hàng trên sông Lòng Tàu, huyện Cần Giờ, TP.Hồ Chí Minh.",
  "content": "Không dừng lại ở 17 hecta, dầu loang đã lan ra gần 30 hecta diện tích rừng ở Cần Giờ. Dầu đã bám vào các gốc cây, thân, rễ. Không chỉ ảnh hưởng đến rừng, dầu loang hiện đã lan đến một số khu vực nuôi thủy sản trên địa bàn, gây thiệt hại hơn 3,3 tấn thủy sản của người dân.Lực lượng ứng phó môi trường đã thu gom hơn 10 mét khối dầu đặc và trên 5 tấn chất thải rắn nhiễm dầu. Đồng thời, phao quây cũng được triển khai để tạm thời cô lập khu vực dầu loang, ngăn nguy cơ lan rộng ra khu vực lân cận.Trước đó, vào khuya ngày 25/4, tàu chở container quốc tịch Panama đang trên hải trình theo hướng từ bến phà Bình Khánh đi ra sông Lòng Tàu khi đến khu vực gần Khoảnh 7 Khoảnh 8, tiểu khu 5b do Ban quản lý Rừng phòng hộ Cần Giờ quản lý (thuộc xã An Thới Đông, huyện Cần Giờ) thì xảy ra va chạm với tàu chở hàng của Hong Kong đang di chuyển theo hướng từ mũi An Thạnh đang di chuyển vào.Tai nạn không gây thương vong và hư hại hàng hóa, nhưng hai tàu đều bị hư hỏng. Trong đó, một tàu biến dạng phần mũi, phương tiện còn lại bị chìm phần lái sau va chạm. Cơ quan chức năng ghi nhận có sự cố làm tràn dầu trên sông.Ngay sau khi sự cố xảy ra, UBND huyện Cần Giờ đã phối hợp cùng với các lực lượng liên quan huy động lực lượng cùng nhiều phương tiện, thiết bị xử lý vụ việc.* Mời quý độc giả theo dõi các chương trình đã phát sóng của Đài Truyền hình Việt Nam trên TV Online và VTVGo!"
}